setup.py
pv/__init__.py
pv/escape.py
pv/i18n.py
pv/template.py
pv/web.py
pv/wsgi.py
pv.egg-info/PKG-INFO
pv.egg-info/SOURCES.txt
pv.egg-info/dependency_links.txt
pv.egg-info/requires.txt
pv.egg-info/top_level.txt