Metadata-Version: 1.0
Name: pv
Version: 0.1.3
Summary: minimal wsgi framework
Home-page: http://github.com/tetsuo/pv
Author: Onur Gunduz
Author-email: ogunduz@gmail.com
License: mit
Platform: UNKNOWN
